Himpunan/__init__.py
Himpunan/code.py
himpunan_team3-0.1.0.dist-info/METADATA
himpunan_team3-0.1.0.dist-info/WHEEL
himpunan_team3-0.1.0.dist-info/top_level.txt
himpunan_team3-0.1.0.dist-info/RECORD
