Metadata-Version: 2.1
Name: himpunan-team3
Version: 0.1.0
Summary: Package Python untuk operasi himpunan
Author: Franklin Jaya, Muh. Ryan Ardiansyah, Tiffany Tjandinegara
Classifier: Programming Language :: Python :: 3
